workflow.py
components/__init__.py
preprocess/__init__.py
preprocess/text_summarization.py
video_s_demo-1.0.0.dist-info/METADATA
video_s_demo-1.0.0.dist-info/WHEEL
video_s_demo-1.0.0.dist-info/top_level.txt
video_s_demo-1.0.0.dist-info/RECORD
