Metadata-Version: 2.1
Name: video-s-demo
Version: 1.0.0
Summary: A package for video summarization
Home-page: https://github.com/HieuTrungCao/Video_Summarization.git
Author: Cao Trung Hieu, Trinh Duc Hiep
Author-email: hieuhocao@gmail.com, 21020169@vnu.edu.vn
License: MIT
Classifier: Programming Language :: Python
Classifier: Programming Language :: Python :: 3
Classifier: Programming Language :: Python :: 3.10
Requires-Dist: requests
